qt_epics/QtEpicsBaseWidget.py
qt_epics/QtEpicsMotorEntry.py
qt_epics/QtEpicsMotorLabel.py
qt_epics/QtEpicsMotorWidget.py
qt_epics/QtEpicsPVEntry.py
qt_epics/QtEpicsPVLabel.py
qt_epics/__init__.py
qt_epics/_version.py
qt_epics/main.py
qt_epics/tests/__init__.py
qt_epics/tests/conftest.py
qt_epics/tests/test_examples.py
qt_epics-0.0.4.dist-info/AUTHORS.rst
qt_epics-0.0.4.dist-info/LICENSE
qt_epics-0.0.4.dist-info/METADATA
qt_epics-0.0.4.dist-info/WHEEL
qt_epics-0.0.4.dist-info/entry_points.txt
qt_epics-0.0.4.dist-info/top_level.txt
qt_epics-0.0.4.dist-info/RECORD
