Metadata-Version: 2.1
Name: qt-epics
Version: 0.0.4
Summary: Qt-based widgets for PyEpics devices
Home-page: https://github.com/JunAishima/qt-epics
Author: Jun Aishima
Author-email: jaishima@bnl.gov
License: BSD (3-clause)
Platform: UNKNOWN
Classifier: Development Status :: 2 - Pre-Alpha
Classifier: Natural Language :: English
Classifier: Programming Language :: Python :: 3
Requires-Python: >=3.4
License-File: LICENSE
License-File: AUTHORS.rst
Requires-Dist: pyepics
Requires-Dist: qtpy
